dataidea/__init__.py
dataidea/core/__init__.py
dataidea/core/packages.py
dataidea/io/__init__.py
dataidea/io/datasets.py
dataidea/sklearn/__init__.py
dataidea/sklearn/models.py
dataidea/utils/__init__.py
dataidea/utils/logging.py
dataidea/utils/printing.py
dataidea/utils/timing.py
dataidea-2025.0.4.dist-info/METADATA
dataidea-2025.0.4.dist-info/WHEEL
dataidea-2025.0.4.dist-info/RECORD
