Metadata-Version: 2.3
Name: dataidea
Version: 2025.0.4
Summary: A package to simplify common data analysis tasks
License: MIT
Author: jumashafara
Author-email: jumashafara0@gmail.com
Requires-Python: >=3.8
Classifier: Development Status :: 3 - Alpha
Classifier: Intended Audience :: Developers
Classifier: Intended Audience :: Science/Research
Classifier: License :: OSI Approved :: MIT License
Classifier: Programming Language :: Python :: 3
Classifier: Programming Language :: Python :: 3.8
Classifier: Programming Language :: Python :: 3.9
Classifier: Programming Language :: Python :: 3.10
Classifier: Programming Language :: Python :: 3.11
Classifier: Programming Language :: Python :: 3.12
Classifier: Programming Language :: Python :: 3.13
Classifier: Topic :: Scientific/Engineering :: Artificial Intelligence
Classifier: Topic :: Scientific/Engineering :: Information Analysis
Provides-Extra: all
Provides-Extra: data
Provides-Extra: viz
Requires-Dist: joblib (>=1.1.0) ; extra == "data" or extra == "all"
Requires-Dist: numpy (>=1.19.0) ; extra == "data" or extra == "all"
Requires-Dist: pandas (>=1.3.0) ; extra == "data" or extra == "all"
Requires-Dist: plotly (>=5.0.0) ; extra == "viz" or extra == "all"
Requires-Dist: python-dotenv (>=0.19.0)
Requires-Dist: requests (>=2.25.0)
Requires-Dist: rich (>=10.0.0)
Requires-Dist: scikit-learn (>=1.0.0) ; extra == "data" or extra == "all"
Requires-Dist: scipy (>=1.7.0) ; extra == "data" or extra == "all"
Project-URL: Documentation, https://docs.dataidea.org
Project-URL: Repository, https://github.com/jumashafara/dataidea
